cc3d/__init__.py
cc3d/fastcc3d.cp314-win32.pyd
cc3d/fastcc3d.pyi
cc3d/py.typed
cc3d/types.py
connected_components_3d-3.26.1.dist-info/licenses/AUTHORS
connected_components_3d-3.26.1.dist-info/licenses/COPYING
connected_components_3d-3.26.1.dist-info/licenses/COPYING.LESSER
connected_components_3d-3.26.1.dist-info/METADATA
connected_components_3d-3.26.1.dist-info/WHEEL
connected_components_3d-3.26.1.dist-info/top_level.txt
connected_components_3d-3.26.1.dist-info/RECORD
