Metadata-Version: 2.4
Name: connected-components-3d
Version: 3.26.1
Summary: Connected components on discrete and continuous multilabel 3D and 2D images. Handles 26, 18, and 6 connected variants; periodic boundaries (4, 8, & 6).
Home-page: https://github.com/seung-lab/connected-components-3d/
Author: William Silversmith
Author-email: ws9@princeton.edu
License: LGPL-3.0-or-later
Keywords: connected-components CCL volumetric-data numpy connectomics image-processing biomedical-image-processing decision-tree union-find sauf 2d 3d
Classifier: Intended Audience :: Developers
Classifier: Development Status :: 5 - Production/Stable
Classifier: Programming Language :: Python
Classifier: Programming Language :: Python :: 3
Classifier: Programming Language :: Python :: 3.9
Classifier: Programming Language :: Python :: 3.10
Classifier: Programming Language :: Python :: 3.11
Classifier: Programming Language :: Python :: 3.12
Classifier: Programming Language :: Python :: 3.13
Classifier: Topic :: Scientific/Engineering
Classifier: Intended Audience :: Science/Research
Classifier: Operating System :: POSIX
Classifier: Operating System :: MacOS
Classifier: Operating System :: Microsoft :: Windows :: Windows 10
Requires-Python: >=3.9,<4.0
License-File: COPYING
License-File: COPYING.LESSER
License-File: AUTHORS
Requires-Dist: numpy
Provides-Extra: stack
Requires-Dist: crackle-codec; extra == "stack"
Requires-Dist: fastremap; extra == "stack"
Dynamic: author
Dynamic: author-email
Dynamic: classifier
Dynamic: description
Dynamic: description-content-type
Dynamic: home-page
Dynamic: keywords
Dynamic: license
Dynamic: license-file
Dynamic: provides-extra
Dynamic: requires-dist
Dynamic: requires-python
Dynamic: summary
